{"name":"selenium","_id":"clti9d6ch0025c9qdddqc7a52","slug":"selenium","path":"tags/selenium/","permalink":"http://lhcfl.github.io/tags/selenium/","posts":[{"title":"Python+selenium实现听力表单自动填写","date":"2020-02-20T23:17:48.000Z","slug":"Python-selenium-auto-commit","published":true,"updated":"2024-03-08T06:10:40.464Z","_id":"clti9d6bv000ic9qdd25xdedo","layout":"post","photos":[],"link":"","excerpt":"<p>本文介绍的是Python+selenium实现听力表单自动填写。</p>","path":"2020/02/20/Python-selenium-auto-commit/","permalink":"http://lhcfl.github.io/2020/02/20/Python-selenium-auto-commit/","__post":true}],"length":1}